homewizard_climate_websocket/__init__.py
homewizard_climate_websocket/const.py
homewizard_climate_websocket/main.py
homewizard_climate_websocket/api/__init__.py
homewizard_climate_websocket/api/api.py
homewizard_climate_websocket/model/__init__.py
homewizard_climate_websocket/model/climate_device.py
homewizard_climate_websocket/model/climate_device_state.py
homewizard_climate_websocket/ws/__init__.py
homewizard_climate_websocket/ws/hw_websocket.py
homewizard_climate_websocket/ws/hw_websocket_payloads.py
homewizard_climate_websocket-0.0.12.dist-info/LICENSE
homewizard_climate_websocket-0.0.12.dist-info/METADATA
homewizard_climate_websocket-0.0.12.dist-info/WHEEL
homewizard_climate_websocket-0.0.12.dist-info/top_level.txt
homewizard_climate_websocket-0.0.12.dist-info/RECORD
